flask_rips/__init__.py
flask_rips/__version__.py
flask_rips/representations/__init__.py
flask_rips/representations/json.py
flask_rips/utils/__init__.py
flask_rips/utils/cors.py
flask_rips/utils/crypto.py
Flask_Rips-0.1.1.dist-info/AUTHORS.md
Flask_Rips-0.1.1.dist-info/LICENSE
Flask_Rips-0.1.1.dist-info/METADATA
Flask_Rips-0.1.1.dist-info/WHEEL
Flask_Rips-0.1.1.dist-info/top_level.txt
Flask_Rips-0.1.1.dist-info/RECORD
