Metadata-Version: 2.1
Name: Flask-Rips
Version: 0.1.1
Summary: Simple framework for minimal REST APIs
Home-page: https://www.github.com/waynerv/flask-rip/
Author: Waynerv
Author-email: ampedee@gmail.com
License: BSD
Platform: any
Classifier: Framework :: Flask
Classifier: Programming Language :: Python :: 3
Classifier: Programming Language :: Python :: 3.4
Classifier: Programming Language :: Python :: 3.5
Classifier: Programming Language :: Python :: 3.6
Classifier: Programming Language :: Python :: 3.7
Classifier: License :: OSI Approved :: BSD License
Requires-Dist: Flask (>=1.0)
Provides-Extra: docs
Requires-Dist: sphinx ; extra == 'docs'
